iostream/__init__.py
iostream-7.1.2.dist-info/LICENSE
iostream-7.1.2.dist-info/METADATA
iostream-7.1.2.dist-info/WHEEL
iostream-7.1.2.dist-info/top_level.txt
iostream-7.1.2.dist-info/RECORD
