Metadata-Version: 2.1
Name: iostream
Version: 7.1.2
Summary: iostream for Python
Home-page: http://www.cubie.xyz:1228
Author: CubieLee
Author-email: liyixiao0608@163.com
License: UNKNOWN
Platform: UNKNOWN
Classifier: Programming Language :: Python :: 3
Classifier: License :: OSI Approved :: MIT License
Classifier: Operating System :: OS Independent
Requires-Python: >=3.4
Requires-Dist: requests
Requires-Dist: selenium
